license.s.HTML
venue.S.HTML
ramps_galactic/___perf/ramps_galactic_1
ramps_galactic/__init__.py
ramps_galactic/__init__v1.py
ramps_galactic/__itinerary/itinerary.S.HTML
ramps_galactic/_book/indexes.s.HTML
ramps_galactic/_clique/__init__.py
ramps_galactic/_clique/group/__init__.py
ramps_galactic/_licenses/gpl-3.0-standalone.html
ramps_galactic/_status/DB/records.json
ramps_galactic/_status/status.proc.py
ramps_galactic/_status/vows/1/status_1.py
ramps_galactic/_status/vows/1/yahoo-finance--BTC-USD.CSV
ramps_galactic/_status/vows/2/status_1.py
ramps_galactic/_status/vows/2/yahoo-finance--SPXU.csv
ramps_galactic/_status/vows/3/status_1.py
ramps_galactic/_status/vows/3/yahoo-finance--UPRO.csv
ramps_galactic/charts/VLOCH.py
ramps_galactic/charts/annotations/vline.py
ramps_galactic/charts/galactic_line.py
ramps_galactic/charts/shapes/rectangle.py
ramps_galactic/charts/shapes/vline.py
ramps_galactic/charts/trend_side_circles.py
ramps_galactic/clouds/Yahoo/VLOCH.py
ramps_galactic/example_data/read.py
ramps_galactic/example_data/yahoo-finance--BTC-USD.CSV
ramps_galactic/furniture/CSV/read.py
ramps_galactic/furniture/DF/reverse.py
ramps_galactic/furniture/places.py
ramps_galactic/license.s.HTML
ramps_galactic/module.MD
ramps_galactic/module.s.HTML
ramps_galactic/status_1.py
ramps_galactic/tendencies/galactic/__init__.py
ramps_galactic/victory_multiplier/purchase_treasure_at_inclines.py
ramps_galactic/victory_multiplier/purchase_treasure_over_span.py
ramps_galactic/victory_multiplier/ramp_v1.py
ramps_galactic/victory_multiplier/ramp_v2.py
ramps_galactic-1.1.2.dist-info/METADATA
ramps_galactic-1.1.2.dist-info/WHEEL
ramps_galactic-1.1.2.dist-info/entry_points.txt
ramps_galactic-1.1.2.dist-info/RECORD
