Metadata-Version: 2.1
Name: ramps_galactic
Version: 1.1.2
Summary: 
License: GPL 3.0
Requires-Python: >=3.10,<3.13
Classifier: License :: Other/Proprietary License
Classifier: Programming Language :: Python :: 3
Classifier: Programming Language :: Python :: 3.10
Classifier: Programming Language :: Python :: 3.11
Classifier: Programming Language :: Python :: 3.12
Requires-Dist: biotech (>=1.0.3,<2.0.0)
Requires-Dist: click (>=8.1.7,<9.0.0)
Requires-Dist: dash (>=2.16.1,<3.0.0)
Requires-Dist: ipython (>=8.23.0,<9.0.0)
Requires-Dist: nbformat (>=5.10.4,<6.0.0)
Requires-Dist: pandas (>=2.2.2,<3.0.0)
Requires-Dist: plotly (>=5.20.0,<6.0.0)
Requires-Dist: rich (>=13.7.1,<14.0.0)
Requires-Dist: yfinance (>=0.2.37,<0.3.0)
Project-URL: GitLab, https://gitlab.com/reptilian_climates/modules_series_4/apoplast
